MANIFEST.in
README.rst
setup.py
django_site_access.egg-info/PKG-INFO
django_site_access.egg-info/SOURCES.txt
django_site_access.egg-info/dependency_links.txt
django_site_access.egg-info/not-zip-safe
django_site_access.egg-info/top_level.txt
site_access/__init__.py
site_access/middleware.py