Metadata-Version: 1.0
Name: django-site-access
Version: 0.1.1
Summary: an app to provide utilities via middleware to control access to your django site
Home-page: http://github.com/pinax/django-site-access/
Author: Patrick Altman
Author-email: paltman@gmail.com
License: BSD
Platform: UNKNOWN
Classifier: Development Status :: 3 - Alpha
Classifier: Environment :: Web Environment
Classifier: Intended Audience :: Developers
Classifier: License :: OSI Approved :: BSD License
Classifier: Operating System :: OS Independent
Classifier: Programming Language :: Python
Classifier: Framework :: Django
